shomei/__init__.py
shomei/art.py
shomei/cli.py
shomei/git_utils.py
shomei/github_api.py
shomei/readme_generator.py
shomei/validators.py
shomei-1.1.0.dist-info/licenses/LICENSE
shomei-1.1.0.dist-info/METADATA
shomei-1.1.0.dist-info/WHEEL
shomei-1.1.0.dist-info/entry_points.txt
shomei-1.1.0.dist-info/top_level.txt
shomei-1.1.0.dist-info/RECORD
