Metadata-Version: 2.4
Name: shomei
Version: 1.1.0
Summary: Show off your coding contributions without leaking corporate IP
Home-page: https://github.com/petarran/shomei
Author: shomei contributors
Author-email: 
License: MIT
Project-URL: Homepage, https://github.com/petarran/shomei
Project-URL: Repository, https://github.com/petarran/shomei
Project-URL: Documentation, https://github.com/petarran/shomei#readme
Project-URL: Issues, https://github.com/petarran/shomei/issues
Keywords: git,github,contributions,privacy,corporate,sanitize
Classifier: Development Status :: 3 - Alpha
Classifier: Intended Audience :: Developers
Classifier: License :: OSI Approved :: MIT License
Classifier: Operating System :: OS Independent
Classifier: Programming Language :: Python :: 3
Classifier: Programming Language :: Python :: 3.10
Classifier: Programming Language :: Python :: 3.11
Classifier: Programming Language :: Python :: 3.12
Classifier: Topic :: Software Development :: Version Control :: Git
Classifier: Topic :: Utilities
Requires-Python: >=3.10
License-File: LICENSE
Requires-Dist: click>=8.0.0
Requires-Dist: requests>=2.25.0
Requires-Dist: rich>=13.0.0
Provides-Extra: dev
Requires-Dist: pytest>=7.0.0; extra == "dev"
Requires-Dist: pytest-cov>=4.0.0; extra == "dev"
Requires-Dist: black>=23.0.0; extra == "dev"
Requires-Dist: flake8>=6.0.0; extra == "dev"
Requires-Dist: mypy>=1.0.0; extra == "dev"
Dynamic: home-page
Dynamic: license-file
Dynamic: requires-python
